LICENSE
MANIFEST.in
README.rst
ptwit.py
setup.py
ptwit.egg-info/PKG-INFO
ptwit.egg-info/SOURCES.txt
ptwit.egg-info/dependency_links.txt
ptwit.egg-info/entry_points.txt
ptwit.egg-info/not-zip-safe
ptwit.egg-info/requires.txt
ptwit.egg-info/top_level.txt