Metadata-Version: 1.1
Name: ptwit
Version: 0.0.9
Summary: A simple twitter command line client
Home-page: https://github.com/ptpt/ptwit
Author: Tao Peng
Author-email: ptpttt+ptwit@gmail.com
License: MIT
Keywords: twitter,command-line,client
Platform: UNKNOWN
Classifier: Development Status :: 4 - Beta
Classifier: License :: OSI Approved :: MIT License
Classifier: Programming Language :: Python :: 2.7
Classifier: Environment :: Console
Classifier: Intended Audience :: End Users/Desktop
Classifier: Topic :: Utilities
